lygeumcli/__init__.py
lygeumcli/commands/__init__.py
lygeumcli/commands/environments.py
lygeumcli/commands/properties.py
lygeumcli/config/__init__.py
lygeumcli/http/__init__.py
lygeumcli/util/__init__.py
sample/__init__.py
lygeumcli-0.1.0b2.dist-info/LICENSE.txt
lygeumcli-0.1.0b2.dist-info/METADATA
lygeumcli-0.1.0b2.dist-info/WHEEL
lygeumcli-0.1.0b2.dist-info/entry_points.txt
lygeumcli-0.1.0b2.dist-info/top_level.txt
lygeumcli-0.1.0b2.dist-info/RECORD
